{
  "indexes": [
    {
      "collectionGroup": "estimates",
      "queryScope": "COLLECTION",
      "fields": [
        { "fieldPath": "customerEmail", "order": "ASCENDING" },
        { "fieldPath": "created_at", "order": "DESCENDING" }
      ]
    },
    {
      "collectionGroup": "invoices",
      "queryScope": "COLLECTION",
      "fields": [
        { "fieldPath": "clientEmail", "order": "ASCENDING" },
        { "fieldPath": "createdAt", "order": "DESCENDING" }
      ]
    },
    {
      "collectionGroup": "invoices",
      "queryScope": "COLLECTION",
      "fields": [
        { "fieldPath": "projectId", "order": "ASCENDING" },
        { "fieldPath": "amount", "order": "ASCENDING" },
        { "fieldPath": "createdAt", "order": "DESCENDING" }
      ]
    },
    {
      "collectionGroup": "vendorBills",
      "queryScope": "COLLECTION",
      "fields": [
        { "fieldPath": "projectId", "order": "ASCENDING" },
        { "fieldPath": "vendorName", "order": "ASCENDING" },
        { "fieldPath": "amount", "order": "ASCENDING" },
        { "fieldPath": "createdAt", "order": "DESCENDING" }
      ]
    },
    {
      "collectionGroup": "tenants",
      "queryScope": "COLLECTION",
      "fields": [
        { "fieldPath": "status", "order": "ASCENDING" },
        { "fieldPath": "createdAt", "order": "DESCENDING" }
      ]
    },
    {
      "collectionGroup": "leads",
      "queryScope": "COLLECTION",
      "fields": [
        { "fieldPath": "tenantId", "order": "ASCENDING" },
        { "fieldPath": "stage", "order": "ASCENDING" },
        { "fieldPath": "createdAt", "order": "DESCENDING" }
      ]
    },
    {
      "collectionGroup": "leads",
      "queryScope": "COLLECTION",
      "fields": [
        { "fieldPath": "tenantId", "order": "ASCENDING" },
        { "fieldPath": "assignedTo", "order": "ASCENDING" },
        { "fieldPath": "createdAt", "order": "DESCENDING" }
      ]
    },
    {
      "collectionGroup": "followUps",
      "queryScope": "COLLECTION",
      "fields": [
        { "fieldPath": "tenantId", "order": "ASCENDING" },
        { "fieldPath": "dueDate", "order": "ASCENDING" }
      ]
    },
    {
      "collectionGroup": "projects",
      "queryScope": "COLLECTION",
      "fields": [
        { "fieldPath": "tenantId", "order": "ASCENDING" },
        { "fieldPath": "status", "order": "ASCENDING" },
        { "fieldPath": "createdAt", "order": "DESCENDING" }
      ]
    },
    {
      "collectionGroup": "contracts",
      "queryScope": "COLLECTION",
      "fields": [
        { "fieldPath": "tenantId", "order": "ASCENDING" },
        { "fieldPath": "status", "order": "ASCENDING" },
        { "fieldPath": "createdAt", "order": "DESCENDING" }
      ]
    }
  ],
  "fieldOverrides": []
}
